Metadata-Version: 2.1
Name: pydemand
Version: 0.0.3
Summary: Retrive region-specific demand data
Home-page: UNKNOWN
Author: Lukas Franken
Author-email: <lukas.franken@ed.ac.uk>
License: UNKNOWN
Keywords: python,demand,energy,systems,electricity,series,prediction,estimation,heat
Platform: UNKNOWN
Classifier: Development Status :: 1 - Planning
Classifier: Intended Audience :: Developers
Classifier: Programming Language :: Python :: 3
Classifier: Operating System :: Unix
Classifier: Operating System :: MacOS :: MacOS X
Classifier: Operating System :: Microsoft :: Windows
License-File: LICENSE
